strands/__init__.py
strands/_async.py
strands/_exception_notes.py
strands/_identifier.py
strands/interrupt.py
strands/py.typed
strands/agent/__init__.py
strands/agent/agent.py
strands/agent/agent_result.py
strands/agent/state.py
strands/agent/conversation_manager/__init__.py
strands/agent/conversation_manager/conversation_manager.py
strands/agent/conversation_manager/null_conversation_manager.py
strands/agent/conversation_manager/sliding_window_conversation_manager.py
strands/agent/conversation_manager/summarizing_conversation_manager.py
strands/event_loop/__init__.py
strands/event_loop/_recover_message_on_max_tokens_reached.py
strands/event_loop/event_loop.py
strands/event_loop/streaming.py
strands/experimental/__init__.py
strands/experimental/agent_config.py
strands/experimental/bidi/__init__.py
strands/experimental/bidi/_async/__init__.py
strands/experimental/bidi/_async/_task_group.py
strands/experimental/bidi/_async/_task_pool.py
strands/experimental/bidi/agent/__init__.py
strands/experimental/bidi/agent/agent.py
strands/experimental/bidi/agent/loop.py
strands/experimental/bidi/io/__init__.py
strands/experimental/bidi/io/audio.py
strands/experimental/bidi/io/text.py
strands/experimental/bidi/models/__init__.py
strands/experimental/bidi/models/gemini_live.py
strands/experimental/bidi/models/model.py
strands/experimental/bidi/models/nova_sonic.py
strands/experimental/bidi/models/openai_realtime.py
strands/experimental/bidi/tools/__init__.py
strands/experimental/bidi/tools/stop_conversation.py
strands/experimental/bidi/types/__init__.py
strands/experimental/bidi/types/agent.py
strands/experimental/bidi/types/events.py
strands/experimental/bidi/types/io.py
strands/experimental/bidi/types/model.py
strands/experimental/hooks/__init__.py
strands/experimental/hooks/events.py
strands/experimental/hooks/multiagent/__init__.py
strands/experimental/hooks/multiagent/events.py
strands/experimental/steering/__init__.py
strands_agents-1.20.0.dist-info/METADATA
strands_agents-1.20.0.dist-info/WHEEL
strands_agents-1.20.0.dist-info/licenses/LICENSE
strands_agents-1.20.0.dist-info/licenses/NOTICE
strands_agents-1.20.0.dist-info/RECORD
