Metadata-Version: 2.4
Name: strands-agents
Version: 1.20.0
Summary: A model-driven approach to building AI agents in just a few lines of code
Project-URL: Homepage, https://github.com/strands-agents/sdk-python
Project-URL: Bug Tracker, https://github.com/strands-agents/sdk-python/issues
Project-URL: Documentation, https://strandsagents.com
Author-email: AWS <opensource@amazon.com>
License: Apache-2.0
License-File: LICENSE
License-File: NOTICE
Classifier: Development Status :: 5 - Production/Stable
Classifier: Intended Audience :: Developers
Classifier: License :: OSI Approved :: Apache Software License
Classifier: Operating System :: OS Independent
Classifier: Programming Language :: Python :: 3
Classifier: Programming Language :: Python :: 3.10
Classifier: Programming Language :: Python :: 3.11
Classifier: Programming Language :: Python :: 3.12
Classifier: Programming Language :: Python :: 3.13
Classifier: Topic :: Scientific/Engineering :: Artificial Intelligence
Classifier: Topic :: Software Development :: Libraries :: Python Modules
Requires-Python: >=3.10
Requires-Dist: boto3<2.0.0,>=1.26.0
Requires-Dist: botocore<2.0.0,>=1.29.0
Requires-Dist: docstring-parser<1.0,>=0.15
Requires-Dist: jsonschema<5.0.0,>=4.0.0
Requires-Dist: mcp<2.0.0,>=1.11.0
Requires-Dist: opentelemetry-api<2.0.0,>=1.30.0
Requires-Dist: opentelemetry-instrumentation-threading<1.00b0,>=0.51b0
Requires-Dist: opentelemetry-sdk<2.0.0,>=1.30.0
Requires-Dist: pydantic<3.0.0,>=2.4.0
Requires-Dist: typing-extensions<5.0.0,>=4.13.2
Requires-Dist: watchdog<7.0.0,>=6.0.0
Provides-Extra: a2a
Requires-Dist: a2a-sdk<0.4.0,>=0.3.0; extra == 'a2a'
Requires-Dist: a2a-sdk[sql]<0.4.0,>=0.3.0; extra == 'a2a'
Requires-Dist: fastapi<1.0.0,>=0.115.12; extra == 'a2a'
Requires-Dist: httpx<1.0.0,>=0.28.1; extra == 'a2a'
Requires-Dist: starlette<1.0.0,>=0.46.2; extra == 'a2a'
Requires-Dist: uvicorn<1.0.0,>=0.34.2; extra == 'a2a'
Provides-Extra: all
Requires-Dist: a2a-sdk<0.4.0,>=0.3.0; extra == 'all'
Requires-Dist: a2a-sdk[sql]<0.4.0,>=0.3.0; extra == 'all'
Requires-Dist: anthropic<1.0.0,>=0.21.0; extra == 'all'
Requires-Dist: boto3-stubs[sagemaker-runtime]<2.0.0,>=1.26.0; extra == 'all'
Requires-Dist: fastapi<1.0.0,>=0.115.12; extra == 'all'
Requires-Dist: google-genai<2.0.0,>=1.32.0; extra == 'all'
Requires-Dist: httpx<1.0.0,>=0.28.1; extra == 'all'
Requires-Dist: litellm<2.0.0,>=1.75.9; extra == 'all'
Requires-Dist: llama-api-client<1.0.0,>=0.1.0; extra == 'all'
Requires-Dist: mistralai>=1.8.2; extra == 'all'
Requires-Dist: ollama<1.0.0,>=0.4.8; extra == 'all'
Requires-Dist: openai<1.110.0,>=1.68.0; extra == 'all'
Requires-Dist: openai<2.0.0,>=1.68.0; extra == 'all'
Requires-Dist: opentelemetry-exporter-otlp-proto-http<2.0.0,>=1.30.0; extra == 'all'
Requires-Dist: sphinx-autodoc-typehints<4.0.0,>=1.12.0; extra == 'all'
Requires-Dist: sphinx-rtd-theme<2.0.0,>=1.0.0; extra == 'all'
Requires-Dist: sphinx<9.0.0,>=5.0.0; extra == 'all'
Requires-Dist: starlette<1.0.0,>=0.46.2; extra == 'all'
Requires-Dist: uvicorn<1.0.0,>=0.34.2; extra == 'all'
Requires-Dist: writer-sdk<3.0.0,>=2.2.0; extra == 'all'
Provides-Extra: anthropic
Requires-Dist: anthropic<1.0.0,>=0.21.0; extra == 'anthropic'
Provides-Extra: bidi
Requires-Dist: aws-sdk-bedrock-runtime; (python_version >= '3.12') and extra == 'bidi'
Requires-Dist: prompt-toolkit<4.0.0,>=3.0.0; extra == 'bidi'
Requires-Dist: pyaudio<1.0.0,>=0.2.13; extra == 'bidi'
Requires-Dist: smithy-aws-core>=0.0.1; (python_version >= '3.12') and extra == 'bidi'
Provides-Extra: bidi-all
Requires-Dist: a2a-sdk<0.4.0,>=0.3.0; extra == 'bidi-all'
Requires-Dist: a2a-sdk[sql]<0.4.0,>=0.3.0; extra == 'bidi-all'
Requires-Dist: aws-sdk-bedrock-runtime; (python_version >= '3.12') and extra == 'bidi-all'
Requires-Dist: fastapi<1.0.0,>=0.115.12; extra == 'bidi-all'
Requires-Dist: google-genai<2.0.0,>=1.32.0; extra == 'bidi-all'
Requires-Dist: httpx<1.0.0,>=0.28.1; extra == 'bidi-all'
Requires-Dist: opentelemetry-exporter-otlp-proto-http<2.0.0,>=1.30.0; extra == 'bidi-all'
Requires-Dist: prompt-toolkit<4.0.0,>=3.0.0; extra == 'bidi-all'
Requires-Dist: pyaudio<1.0.0,>=0.2.13; extra == 'bidi-all'
Requires-Dist: smithy-aws-core>=0.0.1; (python_version >= '3.12') and extra == 'bidi-all'
Requires-Dist: sphinx-autodoc-typehints<4.0.0,>=1.12.0; extra == 'bidi-all'
Requires-Dist: sphinx-rtd-theme<2.0.0,>=1.0.0; extra == 'bidi-all'
Requires-Dist: sphinx<9.0.0,>=5.0.0; extra == 'bidi-all'
Requires-Dist: starlette<1.0.0,>=0.46.2; extra == 'bidi-all'
Requires-Dist: uvicorn<1.0.0,>=0.34.2; extra == 'bidi-all'
Requires-Dist: websockets<16.0.0,>=15.0.0; extra == 'bidi-all'
Provides-Extra: bidi-gemini
Requires-Dist: google-genai<2.0.0,>=1.32.0; extra == 'bidi-gemini'
Provides-Extra: bidi-openai
Requires-Dist: websockets<16.0.0,>=15.0.0; extra == 'bidi-openai'
Provides-Extra: dev
Requires-Dist: commitizen<5.0.0,>=4.4.0; extra == 'dev'
Requires-Dist: hatch<2.0.0,>=1.0.0; extra == 'dev'
Requires-Dist: moto<6.0.0,>=5.1.0; extra == 'dev'
Requires-Dist: mypy<2.0.0,>=1.15.0; extra == 'dev'
Requires-Dist: pre-commit<4.4.0,>=3.2.0; extra == 'dev'
Requires-Dist: pytest-asyncio<1.3.0,>=1.0.0; extra == 'dev'
Requires-Dist: pytest-cov<8.0.0,>=7.0.0; extra == 'dev'
Requires-Dist: pytest-xdist<4.0.0,>=3.0.0; extra == 'dev'
Requires-Dist: pytest<9.0.0,>=8.0.0; extra == 'dev'
Requires-Dist: ruff<0.14.0,>=0.13.0; extra == 'dev'
Provides-Extra: docs
Requires-Dist: sphinx-autodoc-typehints<4.0.0,>=1.12.0; extra == 'docs'
Requires-Dist: sphinx-rtd-theme<2.0.0,>=1.0.0; extra == 'docs'
Requires-Dist: sphinx<9.0.0,>=5.0.0; extra == 'docs'
Provides-Extra: gemini
Requires-Dist: google-genai<2.0.0,>=1.32.0; extra == 'gemini'
Provides-Extra: litellm
Requires-Dist: litellm<2.0.0,>=1.75.9; extra == 'litellm'
Requires-Dist: openai<1.110.0,>=1.68.0; extra == 'litellm'
Provides-Extra: llamaapi
Requires-Dist: llama-api-client<1.0.0,>=0.1.0; extra == 'llamaapi'
Provides-Extra: mistral
Requires-Dist: mistralai>=1.8.2; extra == 'mistral'
Provides-Extra: ollama
Requires-Dist: ollama<1.0.0,>=0.4.8; extra == 'ollama'
Provides-Extra: openai
Requires-Dist: openai<2.0.0,>=1.68.0; extra == 'openai'
Provides-Extra: otel
Requires-Dist: opentelemetry-exporter-otlp-proto-http<2.0.0,>=1.30.0; extra == 'otel'
Provides-Extra: sagemaker
Requires-Dist: boto3-stubs[sagemaker-runtime]<2.0.0,>=1.26.0; extra == 'sagemaker'
Requires-Dist: openai<2.0.0,>=1.68.0; extra == 'sagemaker'
Provides-Extra: writer
Requires-Dist: writer-sdk<3.0.0,>=2.2.0; extra == 'writer'
